<package>
  <description brief="python utilities for ros using the wx environment">
     Provides a collection of frames and widgets that can be embedded in a wxpython program. It depends on MatplotLib to generate nice plots.
     A standalone application for querying and displaying plots from botherder can be found in demos.
     Note: you need WxPython to be installed on your machine
  </description>
  <author>Timothy Hunter/tjhunter@willowgarage.com</author>
  <license>BSD</license>
  <review status="unreviewed" notes=""/>
  <url>http://pr.willowgarage.com/wiki/rospy_wx</url>
  <depend package="rospy" />
  <depend package="std_msgs" />
  <depend package="matplotlib"/>
  <depend package="numpy"/>
  <depend package="scipy"/>
  <depend package="joy" />

  <sysdepend os="ubuntu" version="8.04-hardy" package="liblapack-dev" />
  <sysdepend os="ubuntu" version="8.10-intrepid" package="liblapack-dev" />

</package>
